README.md
setup.py
archieml/__init__.py
archieml.egg-info/PKG-INFO
archieml.egg-info/SOURCES.txt
archieml.egg-info/dependency_links.txt
archieml.egg-info/top_level.txt